vom/__init__.py
vom/__main__.py
vom-2.0.0.dist-info/DESCRIPTION.rst
vom-2.0.0.dist-info/METADATA
vom-2.0.0.dist-info/RECORD
vom-2.0.0.dist-info/WHEEL
vom-2.0.0.dist-info/metadata.json
vom-2.0.0.dist-info/top_level.txt
